{
  "datasets": [
    {
      "name": "afvalwegingen",
      "description":"Afvalwegingenen",
      "table_name": "afval_weging",
      "ordering": "weging_id",
      "pk_field": "weging_id",
      "enable_api": true,
      "name_field": "weging_id",
      "geometry_field": "weging_geometrie",
      "geometry_type": "POINT",
      "enable_geosearch": true,
      "enable_maplayer": true,
      "map_title": "afvalwegingen",
      "map_abstract": "Afvalwegingen",
      "map_layers": [
        {
          "name": "afvalwegingen",
          "title": "Afvalwegingen",
          "abstract": "Afvalwegingen Amsterdam",
          "minscale": 10,
          "maxscale": 400000,
          "label": "afvalwegingen",
          "label_minscale": 10,
          "label_maxscale": 10000
        }
      ]
    },
    {
      "name": "afvalcontainers",
      "description":"Afvalcontainers",
      "table_name": "afval_container",
      "ordering": "container_id",
      "pk_field": "container_id",
      "enable_api": true,
      "name_field": "containertype_naam",
      "geometry_field": "container_geometrie",
      "geometry_type": "POINT",
      "enable_geosearch": true,
      "enable_maplayer": true,
      "map_title": "afvalcontainers",
      "map_abstract": "Afvalcontainers",
      "map_layers": [
        {
          "name": "afvalcontainers",
          "title": "Afvalcontainers",
          "abstract": "Afvalcontainers Amsterdam",
          "minscale": 10,
          "maxscale": 400000,
          "label": "afvalcontainers",
          "label_minscale": 10,
          "label_maxscale": 10000
        }
      ]
    },
    {
      "name": "afvalclusters",
      "description":"Afvalclusters",
      "table_name": "afval_cluster",
      "ordering": "cluster_id",
      "pk_field": "cluster_id",
      "enable_api": true,
      "name_field": "cluster_id",
      "geometry_field": "cluster_geometrie",
      "geometry_type": "POINT",
      "enable_geosearch": true,
      "enable_maplayer": true,
      "map_title": "afvalclusters",
      "map_abstract": "Afvalclusters",
      "map_layers": [
        {
          "name": "afvalclusters",
          "title": "Afvalclusters",
          "abstract": "Afvalclusters Amsterdam",
          "minscale": 10,
          "maxscale": 400000,
          "label": "afvalclusters",
          "label_minscale": 10,
          "label_maxscale": 10000
        }
      ]
    }
  ]
}
